bandsaw/__init__.py
bandsaw/advice.py
bandsaw/config.py
bandsaw/context.py
bandsaw/decorator.py
bandsaw/distribution.py
bandsaw/execution.py
bandsaw/extensions.py
bandsaw/identifier.py
bandsaw/infos.py
bandsaw/interpreter.py
bandsaw/io.py
bandsaw/modules.py
bandsaw/result.py
bandsaw/run.py
bandsaw/runner.py
bandsaw/session.py
bandsaw/tasks.py
bandsaw/user.py
bandsaw/advices/__init__.py
bandsaw/advices/cache.py
bandsaw/advices/log.py
bandsaw/advices/metrics.py
bandsaw/advices/ssh.py
bandsaw/advices/subprocess.py
bandsaw/serialization/__init__.py
bandsaw/serialization/json.py
bandsaw/serialization/pickle.py
bandsaw/serialization/serializer.py
bandsaw/serialization/values.py
bandsaw/tracking/__init__.py
bandsaw/tracking/backend.py
bandsaw/tracking/filesystem.py
bandsaw/tracking/tracker.py
bandsaw-0.3.dist-info/LICENSE
bandsaw-0.3.dist-info/WHEEL
bandsaw-0.3.dist-info/METADATA
bandsaw-0.3.dist-info/RECORD
