Metadata-Version: 2.1
Name: bandsaw
Version: 0.3
Summary: A library for splitting python workflows into separate tasks
Keywords: machine learning,tasks,computation,graph,distributed
Author-email: Christoph Emonds <chris+git@kant.ai>
Requires-Python: >=3.6
Classifier: Intended Audience :: Developers
Classifier: License :: OSI Approved :: MIT License
Classifier: Programming Language :: Python :: 3
Classifier: Topic :: Software Development :: Libraries :: Python Modules
Requires-Dist: tox ; extra == "docs"
Requires-Dist: multimeter ; extra == "multimeter"
Requires-Dist: flit ; extra == "release"
Requires-Dist: tox ; extra == "test"
Project-URL: Documentation, https://docs.kant.ai/bandsaw/latest/
Project-URL: Source, https://gitlab.com/kantai/bandsaw/
Provides-Extra: docs
Provides-Extra: multimeter
Provides-Extra: release
Provides-Extra: test
